guidarktheme/__init__.py
guidarktheme/decorators.py
guidarktheme/widget_template.py
yongshi_guidarktheme-1.1.1.dist-info/LICENSE
yongshi_guidarktheme-1.1.1.dist-info/METADATA
yongshi_guidarktheme-1.1.1.dist-info/WHEEL
yongshi_guidarktheme-1.1.1.dist-info/top_level.txt
yongshi_guidarktheme-1.1.1.dist-info/RECORD
