Metadata-Version: 2.1
Name: yongshi-guidarktheme
Version: 1.1.1
Summary: A dark theme desktop gui package
Home-page: https://github.com/Michael-Yongshi/Gui-Dark-Theme
Author: Michael-Yongshi
Author-email: 4registration@outlook.com
License: UNKNOWN
Platform: UNKNOWN
Classifier: Programming Language :: Python :: 3
Classifier: License :: OSI Approved :: GNU General Public License v3 or later (GPLv3+)
Classifier: Operating System :: OS Independent
Requires-Python: >=3.5
